mymath_custome/__init__.py
mymath_custome/mymath_custome.py
mymath_custome-0.1.0.dist-info/LICENSE
mymath_custome-0.1.0.dist-info/METADATA
mymath_custome-0.1.0.dist-info/WHEEL
mymath_custome-0.1.0.dist-info/top_level.txt
mymath_custome-0.1.0.dist-info/RECORD
