Metadata-Version: 2.1
Name: mymath_custome
Version: 0.1.0
Summary: A simple math operations package
Home-page: https://github.com/xing24xing/math_repo
Author: Khushi Pandey
Author-email: khushipandey260304.email@example.com
Classifier: Programming Language :: Python :: 3
Classifier: License :: OSI Approved :: MIT License
Classifier: Operating System :: OS Independent
Requires-Python: >=3.6
License-File: LICENSE
